similarity_based_rs/__init__.py
similarity_based_rs/add.py
similarity_based_rs-0.1.1.dist-info/LICENSE
similarity_based_rs-0.1.1.dist-info/METADATA
similarity_based_rs-0.1.1.dist-info/WHEEL
similarity_based_rs-0.1.1.dist-info/RECORD
