Metadata-Version: 2.1
Name: similarity-based-rs
Version: 0.1.1
Summary: An out-of-the-box recommendation system based on item similarity.
Author: MikeXydas
Author-email: mikexydas@gmail.com
Requires-Python: >=3.8,<4.0
Classifier: Programming Language :: Python :: 3
Classifier: Programming Language :: Python :: 3.8
Classifier: Programming Language :: Python :: 3.9
Classifier: Programming Language :: Python :: 3.10
Classifier: Programming Language :: Python :: 3.11
Requires-Dist: numpy (>=1.24.3,<2.0.0)
Requires-Dist: pandas (>=2.0.2,<3.0.0)
Requires-Dist: pydantic (>=2.3.0,<3.0.0)
